mwdblib/__init__.py
mwdblib/__version__.py
mwdblib/blob.py
mwdblib/comment.py
mwdblib/config.py
mwdblib/core.py
mwdblib/exc.py
mwdblib/file.py
mwdblib/karton.py
mwdblib/object.py
mwdblib/py.typed
mwdblib/share.py
mwdblib/util.py
mwdblib/api/__init__.py
mwdblib/api/api.py
mwdblib/api/options.py
mwdblib/cli/__init__.py
mwdblib/cli/attribute.py
mwdblib/cli/comment.py
mwdblib/cli/fetch.py
mwdblib/cli/get.py
mwdblib/cli/link.py
mwdblib/cli/list.py
mwdblib/cli/login.py
mwdblib/cli/main.py
mwdblib/cli/metakey.py
mwdblib/cli/search.py
mwdblib/cli/share.py
mwdblib/cli/tag.py
mwdblib/cli/types.py
mwdblib/cli/upload.py
mwdblib/cli/formatters/__init__.py
mwdblib/cli/formatters/abstract.py
mwdblib/cli/formatters/attribute.py
mwdblib/cli/formatters/formatters.py
mwdblib/cli/formatters/json.py
mwdblib/cli/formatters/short.py
mwdblib/cli/formatters/tabular.py
mwdblib-4.6.0.dist-info/LICENSE
mwdblib-4.6.0.dist-info/METADATA
mwdblib-4.6.0.dist-info/WHEEL
mwdblib-4.6.0.dist-info/entry_points.txt
mwdblib-4.6.0.dist-info/top_level.txt
mwdblib-4.6.0.dist-info/RECORD
