Metadata-Version: 2.1
Name: mwdblib
Version: 4.6.0
Summary: MWDB API bindings for Python
Home-page: https://github.com/CERT-Polska/mwdblib
Author: psrok1
Classifier: Programming Language :: Python :: 3
Classifier: Operating System :: OS Independent
Classifier: License :: OSI Approved :: MIT License
Requires-Python: >=3.10
License-File: LICENSE
Requires-Dist: keyring >=18.0.0
Requires-Dist: requests
Provides-Extra: cli
Requires-Dist: beautifultable >=1.0.0 ; extra == 'cli'
Requires-Dist: click-default-group ; extra == 'cli'
Requires-Dist: click >=7.0 ; extra == 'cli'
Requires-Dist: humanize >=0.5.1 ; extra == 'cli'
